{
    "subject": "Osnovni pozdravi i svakodnevne rečenice 50",
    "entries": [
        {
            "text": "Zdravo.",
            "note": "Polite greeting"
        },
        {
            "text": "Drago mi je što smo se upoznali.",
            "note": "First meeting"
        },
        {
            "text": "Dugo se nismo videli.",
            "note": "Reunion"
        },
        {
            "text": "Hvala Vam.",
            "note": "Formal"
        },
        {
            "text": "Žao mi je.",
            "note": "Formal"
        },
        {
            "text": "Izvinite.",
            "note": "Attention"
        },
        {
            "text": "Kako ste?",
            "note": "Greetings"
        },
        {
            "text": "Dobro sam, hvala.",
            "note": ""
        },
        {
            "text": "Kako se zovete?",
            "note": ""
        },
        {
            "text": "Zovem se ...",
            "note": ""
        },
        {
            "text": "Odakle ste?",
            "note": ""
        },
        {
            "text": "Ja sam iz Amerike.",
            "note": ""
        },
        {
            "text": "Doviđenja.",
            "note": "To someone leaving"
        },
        {
            "text": "Doviđenja.",
            "note": "To someone staying"
        },
        {
            "text": "Da.",
            "note": "Positive"
        },
        {
            "text": "Ne.",
            "note": "Negative"
        },
        {
            "text": "Možda.",
            "note": "Guess"
        },
        {
            "text": "Razumem.",
            "note": ""
        },
        {
            "text": "Ne znam.",
            "note": ""
        },
        {
            "text": "Molim vas, pomozite mi.",
            "note": ""
        },
        {
            "text": "Samo trenutak, molim vas.",
            "note": ""
        },
        {
            "text": "Koliko ovo košta?",
            "note": "Shopping"
        },
        {
            "text": "Gde je kupatilo?",
            "note": ""
        },
        {
            "text": "Gladan sam.",
            "note": ""
        },
        {
            "text": "Žedan sam.",
            "note": ""
        },
        {
            "text": "Ukusno je.",
            "note": ""
        },
        {
            "text": "Sviđa mi se.",
            "note": ""
        },
        {
            "text": "U redu je.",
            "note": ""
        },
        {
            "text": "Srećno.",
            "note": ""
        },
        {
            "text": "Koliko je sati sada?",
            "note": ""
        },
        {
            "text": "Danas je lepo vreme.",
            "note": ""
        },
        {
            "text": "Hladno je.",
            "note": ""
        },
        {
            "text": "Vruće je.",
            "note": ""
        },
        {
            "text": "Umoran sam.",
            "note": ""
        },
        {
            "text": "Srećan sam.",
            "note": ""
        },
        {
            "text": "Čestitam.",
            "note": ""
        },
        {
            "text": "Srećan rođendan.",
            "note": ""
        },
        {
            "text": "Želim Vam prijatan dan.",
            "note": ""
        },
        {
            "text": "Vidimo se sutra.",
            "note": ""
        },
        {
            "text": "Čuvajte se.",
            "note": ""
        },
        {
            "text": "Da li govorite engleski?",
            "note": ""
        },
        {
            "text": "Govorim samo malo korejski.",
            "note": ""
        },
        {
            "text": "Molim vas, govorite sporije.",
            "note": ""
        },
        {
            "text": "Šta ovo znači?",
            "note": ""
        },
        {
            "text": "Kako se to kaže na korejskom?",
            "note": ""
        },
        {
            "text": "Volim te.",
            "note": ""
        },
        {
            "text": "Molim vas, sačekajte.",
            "note": ""
        },
        {
            "text": "Nema na čemu.",
            "note": ""
        },
        {
            "text": "Ne, u redu je.",
            "note": ""
        },
        {
            "text": "Imam pitanje.",
            "note": ""
        }
    ]
}